{
  "publicPath": "https://file.calibur.tv/smile/",
  "all": [
    "../server/index.spa.html",
    "../server/index.ssr.html",
    "03c6b804c16ac14e2e9d.js",
    "0adf1a4e5e2e2282b8bd.js",
    "117ab9dffc5c75e2e990.js",
    "15a50ce76ce95e11a03a.js",
    "21b882d1faf3273140b8.js",
    "23d97e56fdb63ff42020.js",
    "2f9a90bbc718a9fa6090.js",
    "3483728136924fd21585.js",
    "34956d24d7edf922954c.js",
    "3b7fbc8c555be3306220.js",
    "53c72caf02b39b05df5b.js",
    "5c1450d582fcb9dc9f96.js",
    "5ca770cdc1ceb3654df6.js",
    "656243098c1770139b21.js",
    "6c227cdc12a3fab0fddb.js",
    "7058cea4407b80be1cc0.js",
    "73ec61f8ebc688bd11df.js",
    "788e5ec3f63c00033bcb.js",
    "7e0b5aaa4dc45800ddb8.js",
    "857ede6259f7e8fd1998.js",
    "8a69b6a5ffeb5ce37cc0.js",
    "8af30249a80d46927592.js",
    "92da7ee2684eee7f19f9.js",
    "95e51a1f2db5d8654581.js",
    "LICENSES",
    "a534d62f8f28d614a214.js",
    "ad1dd0feea92003ffe63.js",
    "bffa019355526fe45764.js",
    "e4ea8fcc42d0f8dd381c.js",
    "f5a066701973d73408dd.js",
    "ff01147a6b4f058ea8c7.js"
  ],
  "initial": [
    "bffa019355526fe45764.js",
    "3b7fbc8c555be3306220.js",
    "5ca770cdc1ceb3654df6.js",
    "23d97e56fdb63ff42020.js"
  ],
  "async": [
    "03c6b804c16ac14e2e9d.js",
    "0adf1a4e5e2e2282b8bd.js",
    "117ab9dffc5c75e2e990.js",
    "15a50ce76ce95e11a03a.js",
    "21b882d1faf3273140b8.js",
    "2f9a90bbc718a9fa6090.js",
    "3483728136924fd21585.js",
    "34956d24d7edf922954c.js",
    "53c72caf02b39b05df5b.js",
    "5c1450d582fcb9dc9f96.js",
    "656243098c1770139b21.js",
    "6c227cdc12a3fab0fddb.js",
    "7058cea4407b80be1cc0.js",
    "73ec61f8ebc688bd11df.js",
    "788e5ec3f63c00033bcb.js",
    "7e0b5aaa4dc45800ddb8.js",
    "857ede6259f7e8fd1998.js",
    "8a69b6a5ffeb5ce37cc0.js",
    "8af30249a80d46927592.js",
    "92da7ee2684eee7f19f9.js",
    "95e51a1f2db5d8654581.js",
    "a534d62f8f28d614a214.js",
    "ad1dd0feea92003ffe63.js",
    "e4ea8fcc42d0f8dd381c.js",
    "f5a066701973d73408dd.js",
    "ff01147a6b4f058ea8c7.js"
  ],
  "modules": {
    "11217334": [
      19
    ],
    "12431467": [
      7
    ],
    "19127515": [
      24
    ],
    "28349838": [
      22
    ],
    "29418593": [
      7
    ],
    "37431440": [
      11
    ],
    "49420837": [
      11
    ],
    "63245637": [
      11
    ],
    "71851020": [
      17
    ],
    "74871540": [
      11
    ],
    "79938307": [
      13
    ],
    "81883058": [
      14
    ],
    "90955906": [
      11
    ],
    "3a010dac": [
      7
    ],
    "124e5295": [
      11
    ],
    "6f370d31": [
      11
    ],
    "54f0ac28": [
      11
    ],
    "6d2962e2": [
      11
    ],
    "1a8a7f94": [
      11
    ],
    "53d93926": [
      11
    ],
    "26e1e28a": [
      11
    ],
    "0361f436": [
      11
    ],
    "4ce68b47": [
      11
    ],
    "47f48e78": [
      11
    ],
    "c4144722": [
      11
    ],
    "2bba0d4a": [
      11
    ],
    "997000a8": [
      11
    ],
    "9f3731e2": [
      11
    ],
    "5fc3cd77": [
      11
    ],
    "be8e635e": [
      11
    ],
    "08976508": [
      11
    ],
    "370f555c": [
      11
    ],
    "44c9393a": [
      11
    ],
    "83b93d2e": [
      7
    ],
    "4086c90a": [
      7
    ],
    "09638930": [
      7
    ],
    "296d3250": [
      7
    ],
    "707f7e9f": [
      7
    ],
    "1d08d6da": [
      7
    ],
    "1dc862fa": [
      7
    ],
    "cda9a976": [
      7
    ],
    "20f637ba": [
      7
    ],
    "0420968e": [
      7
    ],
    "01e87044": [
      7
    ],
    "384bf3b8": [
      7
    ],
    "3f3fa777": [
      7
    ],
    "b8b0fa3a": [
      7
    ],
    "65660a26": [
      7
    ],
    "0d7e48f8": [
      7
    ],
    "b9dcdd5e": [
      7
    ],
    "b2929edc": [
      7
    ],
    "02e44889": [
      7
    ],
    "6a2ac987": [
      7
    ],
    "2f8f2786": [
      7
    ],
    "8bbc44f0": [
      7
    ],
    "e573ec18": [
      7
    ],
    "39711c24": [
      7
    ],
    "2870ec5a": [
      7
    ],
    "26445b32": [
      7
    ],
    "47d469f9": [
      7
    ],
    "cd1388b8": [
      7
    ],
    "cb76b8c2": [
      7
    ],
    "17d8f4a9": [
      7
    ],
    "41c016d1": [
      7
    ],
    "9f4c42ec": [
      7
    ],
    "4df5db58": [
      11
    ],
    "1d429c5f": [
      11
    ],
    "0c03a82c": [
      14
    ],
    "5709e04b": [
      14
    ],
    "3023fc8c": [
      14
    ],
    "dec9ed6a": [
      11
    ],
    "16876cac": [
      11
    ],
    "3d799ad5": [
      11
    ],
    "39e3b82c": [
      11
    ],
    "6d8c28ae": [
      11
    ],
    "da8848cc": [
      11
    ],
    "9c3172ac": [
      11
    ],
    "1b56b304": [
      11
    ],
    "aa328b9a": [
      11
    ],
    "212a25a0": [
      11
    ],
    "5936ecf8": [
      11
    ],
    "527f8644": [
      11
    ],
    "5407d911": [
      11
    ],
    "73fa3eb1": [
      11
    ],
    "12b74591": [
      14
    ],
    "e17f299a": [
      14
    ],
    "b3b00f22": [
      11
    ],
    "5fc052e2": [
      11
    ],
    "81a8320e": [
      11
    ],
    "20571c2c": [
      11
    ],
    "3cfda7be": [
      11
    ],
    "6cac6038": [
      11
    ],
    "c6a5f000": [
      11
    ],
    "3464832e": [
      11
    ],
    "9076cc1a": [
      11
    ],
    "0a9f248e": [
      11
    ],
    "1500d2ee": [
      14
    ],
    "4ba07f2b": [
      11
    ],
    "58dfee3f": [
      11
    ],
    "15b6b9ac": [
      14
    ],
    "cd9b4ee2": [
      11
    ],
    "cbb40caa": [
      11
    ],
    "f220fd9c": [
      11
    ],
    "a2684fd6": [
      11
    ],
    "4cd96c01": [
      11
    ],
    "f09a7938": [
      11
    ],
    "2e0f8eb0": [
      11
    ],
    "1f9f76a6": [
      11
    ],
    "84729f72": [
      11
    ],
    "23f83252": [
      11
    ],
    "a422321c": [
      11
    ],
    "2fd58a0e": [
      11
    ],
    "7b95e09c": [
      11
    ],
    "e2051ba2": [
      11
    ],
    "5cffe75c": [
      11
    ],
    "9aa35f58": [
      11
    ],
    "50e6ba1f": [
      11
    ],
    "1338daea": [
      11
    ],
    "d21ca04a": [
      7
    ],
    "60f4b76d": [
      7
    ],
    "78457b3a": [
      11
    ],
    "425b7433": [
      11
    ],
    "74af09ee": [
      11
    ],
    "2180b99e": [
      11
    ],
    "636a4182": [
      11
    ],
    "b5892f56": [
      11
    ],
    "3aab9dfa": [
      11
    ],
    "1e777710": [
      11
    ],
    "e8930af0": [
      11
    ],
    "00cafd6d": [
      11
    ],
    "437cb50c": [
      11
    ],
    "66f378f1": [
      11
    ],
    "10762a40": [
      11
    ],
    "96e2720e": [
      11
    ],
    "3c08a574": [
      11
    ],
    "defcb1a0": [
      11
    ],
    "a21bac8c": [
      11
    ],
    "8722180a": [
      11
    ],
    "2179f1d1": [
      11
    ],
    "3998d7ca": [
      11
    ],
    "27ff73d2": [
      11
    ],
    "ec94d17c": [
      11
    ],
    "b86a6d86": [
      11
    ],
    "9cf82478": [
      11
    ],
    "5f40f880": [
      11
    ],
    "6de2d821": [
      7
    ],
    "1715f7c5": [
      14
    ],
    "e0f710b2": [
      11
    ],
    "0d849304": [
      11
    ],
    "2e9794fd": [
      11
    ],
    "5161995b": [
      11
    ],
    "740e29af": [
      11
    ],
    "453517ce": [
      11
    ],
    "5f0e4f9a": [
      11
    ],
    "74ebb47b": [
      11
    ],
    "43cc0eb8": [
      11
    ],
    "1fa13b1c": [
      11
    ],
    "5ad0c49a": [
      11
    ],
    "19758ec0": [
      11
    ],
    "3c2a35f5": [
      11
    ],
    "1ab8eb8e": [
      11
    ],
    "4866aa68": [
      11
    ],
    "59104f6a": [
      11
    ],
    "3c1157ac": [
      11
    ],
    "6fc1c2c0": [
      11
    ],
    "70aee9f6": [
      11
    ],
    "40f8855a": [
      11
    ],
    "0eafc870": [
      11
    ],
    "88f435d4": [
      11
    ],
    "38e7e168": [
      11
    ],
    "480132c4": [
      11
    ],
    "be691254": [
      11
    ],
    "6e23840f": [
      11
    ],
    "027533ee": [
      11
    ],
    "84b52944": [
      11
    ],
    "063bd2bc": [
      11
    ],
    "be42a8a4": [
      11
    ],
    "01a96b93": [
      11
    ],
    "9b7d6cda": [
      11
    ],
    "5201c250": [
      11
    ],
    "c8a95d80": [
      11
    ],
    "41150bd4": [
      11
    ],
    "657deccf": [
      11
    ],
    "9a8358a4": [
      11
    ],
    "682719d0": [
      11
    ],
    "1530ea0c": [
      14
    ],
    "183399c3": [
      7
    ],
    "0a965e28": [
      11
    ],
    "5e0804f0": [
      11
    ],
    "f37f507c": [
      11
    ],
    "1581637e": [
      11
    ],
    "48d9c27c": [
      11
    ],
    "d01f8f52": [
      11
    ],
    "5074b669": [
      11
    ],
    "13a1e528": [
      11
    ],
    "609a0c0f": [
      14
    ],
    "3fceb88e": [
      11
    ],
    "59b79160": [
      14
    ],
    "242b964d": [
      14
    ],
    "774beee8": [
      14
    ],
    "81863e12": [
      14
    ],
    "66d33e00": [
      11
    ],
    "70ffb618": [
      11
    ],
    "d07c648e": [
      11
    ],
    "2df92de4": [
      11
    ],
    "61a74a7d": [
      11
    ],
    "5da0e2ba": [
      11
    ],
    "33f761fc": [
      11
    ],
    "56284d48": [
      11
    ],
    "01a3d328": [
      11
    ],
    "483760fd": [
      11
    ],
    "682ce779": [
      11
    ],
    "23a36203": [
      11
    ],
    "ec11f0a8": [
      11
    ],
    "4a95b443": [
      7
    ],
    "7605f570": [
      7
    ],
    "a1918aa8": [
      11
    ],
    "2d60f209": [
      11
    ],
    "5060e930": [
      11
    ],
    "eedb2fa8": [
      11
    ],
    "e25a021a": [
      11
    ],
    "542c5260": [
      11
    ],
    "2543c6db": [
      11
    ],
    "02da218f": [
      11
    ],
    "5b388f66": [
      11
    ],
    "3080e4e0": [
      11
    ],
    "2bc7a946": [
      11
    ],
    "376cf570": [
      11
    ],
    "9cbce150": [
      11
    ],
    "716d35b4": [
      11
    ],
    "4ba2b56a": [
      11
    ],
    "c88e1d04": [
      11
    ],
    "2d750edc": [
      11
    ],
    "2cc5a251": [
      11
    ],
    "2d25c8db": [
      11
    ],
    "d85ea77e": [
      11
    ],
    "1c19066e": [
      11
    ],
    "76384d60": [
      11
    ],
    "0727feab": [
      7
    ],
    "1890545c": [
      7
    ],
    "4e20ef37": [
      7
    ],
    "5617989e": [
      7
    ],
    "a7a25434": [
      7
    ],
    "3d8c58d9": [
      7
    ],
    "7d9b333a": [
      14
    ],
    "b86a823a": [
      14
    ],
    "3a292eb9": [
      7
    ],
    "3c348136": [
      11
    ],
    "d4f1f9a6": [
      11
    ],
    "6ab4a543": [
      11
    ],
    "139b1124": [
      11
    ],
    "eab7a366": [
      11
    ],
    "1b13dba0": [
      11
    ],
    "adba0600": [
      11
    ],
    "42fbc8f1": [
      11
    ],
    "30e8e021": [
      11
    ],
    "62bcd7c2": [
      11
    ],
    "fd8a53d4": [
      11
    ],
    "5a8593d4": [
      11
    ],
    "b7850114": [
      11
    ],
    "3af8f9ae": [
      11
    ],
    "aedeb914": [
      11
    ],
    "260f971f": [
      14
    ],
    "1c4b1af0": [
      14
    ],
    "e9f27986": [
      14
    ],
    "9a0a9e96": [
      7
    ],
    "5d5c4e34": [
      7
    ],
    "64f7dee0": [
      17
    ],
    "61d00072": [
      12
    ],
    "c9d509ce": [
      12
    ],
    "83f5345e": [
      22
    ],
    "60d3e5bb": [
      25
    ],
    "682784b0": [
      2
    ],
    "a7f10dd6": [
      10
    ],
    "4e42741a": [
      15
    ],
    "52b4dd13": [
      32
    ],
    "55a30d9c": [
      8
    ],
    "1d2e8465": [
      18
    ],
    "3b98767b": [
      3
    ],
    "44dd83c7": [
      4
    ],
    "744e60df": [
      21
    ],
    "591d3900": [
      31
    ],
    "bb16205e": [
      9
    ],
    "8b214be6": [
      27
    ],
    "667261c1": [
      24
    ],
    "14800da1": [
      24
    ],
    "0cd77753": [
      19
    ],
    "eb8f5338": [
      19
    ],
    "93a4507a": [
      17
    ],
    "8ba4926c": [
      17
    ],
    "953ade92": [
      17
    ],
    "19fd790c": [
      13
    ],
    "6ac47411": [
      22
    ],
    "58cfcdbe": [
      22
    ],
    "2d9adbdb": [
      12
    ],
    "9cfe410a": [
      25
    ],
    "0469cf24": [
      25
    ],
    "7e379be8": [
      2
    ],
    "42323fd5": [
      2
    ],
    "58c68755": [
      10
    ],
    "46d1e102": [
      10
    ],
    "77fd009a": [
      15
    ],
    "d13d48b4": [
      15
    ],
    "3dd796d3": [
      32
    ],
    "113772c6": [
      32
    ],
    "5987311c": [
      8
    ],
    "990dbac2": [
      8
    ],
    "3e4343b6": [
      18
    ],
    "08390898": [
      18
    ],
    "26bb303b": [
      3
    ],
    "0bc9e7a4": [
      3
    ],
    "d4eb04f2": [
      4
    ],
    "3c56930c": [
      4
    ],
    "24fa41c2": [
      21
    ],
    "f3c2fce8": [
      21
    ],
    "351f01c0": [
      31
    ],
    "78c23aa6": [
      31
    ],
    "4f33fe11": [
      9
    ],
    "3d3f57be": [
      9
    ],
    "50cd5e66": [
      23
    ],
    "634c50c4": [
      23
    ],
    "4d5361da": [
      23
    ],
    "1c1cf84d": [
      27
    ],
    "aac64d8c": [
      27
    ],
    "1fba3933": [
      24
    ],
    "a9258dac": [
      24
    ],
    "a8dc6d98": [
      24
    ],
    "40b23ffe": [
      24
    ],
    "7842826e": [
      24
    ],
    "762dabe1": [
      24
    ],
    "04ad8cce": [
      24
    ],
    "50bbb104": [
      19
    ],
    "8b489a1e": [
      19
    ],
    "99ae0760": [
      19
    ],
    "7026b67d": [
      19
    ],
    "0ff7378b": [
      17
    ],
    "f75b3012": [
      17
    ],
    "a4bb3a58": [
      17
    ],
    "713472e7": [
      19
    ],
    "2e322d14": [
      19
    ],
    "6d58b279": [
      17
    ],
    "678e10e4": [
      19
    ],
    "c4ce26de": [
      19
    ],
    "ad464fa2": [
      17
    ],
    "95ef07aa": [
      19
    ],
    "343f1fb2": [
      17
    ],
    "55677be5": [
      19
    ],
    "e91b50dc": [
      19
    ],
    "0e445229": [
      19
    ],
    "311d571d": [
      19
    ],
    "672832ca": [
      19
    ],
    "7ea5a701": [
      19
    ],
    "81ba54da": [
      19
    ],
    "f9c50d00": [
      19
    ],
    "283416b8": [
      19
    ],
    "7a65d591": [
      19
    ],
    "55ef7910": [
      30
    ],
    "12ed333d": [
      30
    ],
    "52f2373f": [
      13
    ],
    "cec35026": [
      13
    ],
    "31dda486": [
      13
    ],
    "6743f3c3": [
      13
    ],
    "b0c8821c": [
      13
    ],
    "08e28bc5": [
      13
    ],
    "5b50abc0": [
      13
    ],
    "47f87ff1": [
      6
    ],
    "4b1767b8": [
      6
    ],
    "414967e9": [
      6
    ],
    "19e89e20": [
      5
    ],
    "3b9677cd": [
      6
    ],
    "5148599e": [
      19
    ],
    "7a7a7a96": [
      19
    ],
    "01140c36": [
      19
    ],
    "4a7f0546": [
      19
    ],
    "b08055dc": [
      19
    ],
    "67049c40": [
      19
    ],
    "0d90afcf": [
      19
    ],
    "29ab25d4": [
      19
    ],
    "6c778a7f": [
      19
    ],
    "551e697a": [
      19
    ],
    "96562c4c": [
      19
    ],
    "196c9b74": [
      19
    ],
    "36422b36": [
      19
    ],
    "6a44e55a": [
      19
    ],
    "11cf1c9b": [
      19
    ],
    "393265d3": [
      19
    ],
    "7e8222dd": [
      19
    ],
    "2d3def21": [
      19
    ],
    "00721472": [
      4
    ],
    "2fe44f1a": [
      4
    ],
    "5f878dfc": [
      4
    ],
    "23a47bc3": [
      4
    ],
    "20a55c16": [
      4
    ],
    "509e4df8": [
      4
    ],
    "f73469d4": [
      4
    ],
    "770d32fc": [
      4
    ],
    "5728b266": [
      4
    ],
    "49d689af": [
      4
    ],
    "41992ca4": [
      24
    ],
    "699b9020": [
      24
    ],
    "355e8bf0": [
      24
    ],
    "c9927ac0": [
      24
    ],
    "e4cad596": [
      24
    ],
    "c54f2264": [
      24
    ],
    "47514c18": [
      24
    ],
    "a6980f30": [
      24
    ],
    "17b0fec8": [
      24
    ],
    "448b325e": [
      22
    ],
    "5934a1d0": [
      22
    ],
    "094136e8": [
      22
    ],
    "deb519f6": [
      22
    ],
    "2d752628": [
      25
    ],
    "cbd11068": [
      25
    ],
    "53270e88": [
      25
    ],
    "6cda5f1c": [
      25
    ],
    "25f0653b": [
      25
    ],
    "bdb4c516": [
      2
    ],
    "1d40afb4": [
      2
    ],
    "632e4321": [
      2
    ],
    "7c278a64": [
      2
    ],
    "4d74a14e": [
      2
    ],
    "440356a2": [
      10
    ],
    "4e9cc32e": [
      10
    ],
    "8f4fc158": [
      10
    ],
    "8c8385ce": [
      10
    ],
    "7597e341": [
      10
    ],
    "0b35ed24": [
      15
    ],
    "dfa59db6": [
      15
    ],
    "f8e44760": [
      15
    ],
    "5e972f16": [
      15
    ],
    "6e469603": [
      15
    ],
    "582bcc44": [
      32
    ],
    "1d94ad88": [
      32
    ],
    "62697da0": [
      32
    ],
    "31bce08c": [
      32
    ],
    "8cf80a3a": [
      32
    ],
    "449fd6ff": [
      8
    ],
    "4b19506a": [
      8
    ],
    "6e4b3117": [
      8
    ],
    "fb51d1cc": [
      8
    ],
    "3cfd3684": [
      8
    ],
    "0d42c1d4": [
      18
    ],
    "47646dd0": [
      18
    ],
    "676321c4": [
      18
    ],
    "104105c0": [
      18
    ],
    "5845d15e": [
      18
    ],
    "675e3fac": [
      3
    ],
    "7bc45f29": [
      3
    ],
    "3c79f2c8": [
      3
    ],
    "8768d30e": [
      3
    ],
    "2732ac7b": [
      3
    ],
    "c690d528": [
      21
    ],
    "c0920434": [
      21
    ],
    "66a640ec": [
      21
    ],
    "7016b096": [
      21
    ],
    "390b5c37": [
      21
    ],
    "6424e74d": [
      31
    ],
    "00978cc4": [
      31
    ],
    "65107d49": [
      31
    ],
    "5ec7d118": [
      31
    ],
    "0d5a5876": [
      31
    ],
    "5c4460f6": [
      20
    ],
    "c80808ee": [
      20
    ],
    "16695bd1": [
      20
    ],
    "7d089a39": [
      20
    ],
    "58adc084": [
      20
    ],
    "e4058744": [
      9
    ],
    "19ebc6f1": [
      9
    ],
    "2b72e518": [
      9
    ],
    "0a0f34be": [
      9
    ],
    "2e9aadf6": [
      9
    ],
    "a788c1a4": [
      28
    ],
    "e1a9401e": [
      28
    ],
    "bd4b6770": [
      28
    ],
    "7037fea1": [
      28
    ],
    "5e9a1035": [
      28
    ],
    "2308ddcc": [
      27
    ],
    "7bbafa15": [
      27
    ],
    "0b3cf7c8": [
      27
    ],
    "4bbf84c5": [
      27
    ],
    "baa9416e": [
      27
    ],
    "216fcfc4": [
      16
    ],
    "529006cd": [
      16
    ],
    "65262a18": [
      16
    ],
    "b3352d06": [
      16
    ],
    "6ecea3c5": [
      16
    ],
    "e9ef41f4": [
      30
    ],
    "2dec1762": [
      30
    ],
    "f5e1c886": [
      30
    ],
    "dad6b3f0": [
      30
    ]
  },
  "assetsMapping": {
    "03c6b804c16ac14e2e9d.js": "4236c968",
    "0adf1a4e5e2e2282b8bd.js": "3abf3429",
    "117ab9dffc5c75e2e990.js": "ef652aa2",
    "15a50ce76ce95e11a03a.js": "bba68bf6",
    "21b882d1faf3273140b8.js": "bba68bf6",
    "23d97e56fdb63ff42020.js": "1a3ae26b",
    "2f9a90bbc718a9fa6090.js": "9a20429c",
    "3483728136924fd21585.js": "9e3c2dde",
    "34956d24d7edf922954c.js": "cd107556",
    "3b7fbc8c555be3306220.js": "0859c165",
    "53c72caf02b39b05df5b.js": "4801d52b",
    "5c1450d582fcb9dc9f96.js": "bba68bf6",
    "5ca770cdc1ceb3654df6.js": "7ea1d828",
    "656243098c1770139b21.js": "3ab85da1",
    "6c227cdc12a3fab0fddb.js": "2a130dde",
    "7058cea4407b80be1cc0.js": "7dc2ba61",
    "73ec61f8ebc688bd11df.js": "748573da",
    "788e5ec3f63c00033bcb.js": "06677824",
    "7e0b5aaa4dc45800ddb8.js": "9e3fb090",
    "857ede6259f7e8fd1998.js": "1d2d125f",
    "8a69b6a5ffeb5ce37cc0.js": "ce4a41de",
    "8af30249a80d46927592.js": "3990566c",
    "92da7ee2684eee7f19f9.js": "6bdfd521",
    "95e51a1f2db5d8654581.js": "23c1c72e",
    "a534d62f8f28d614a214.js": "6bdc928d",
    "ad1dd0feea92003ffe63.js": "9e3b983e",
    "bffa019355526fe45764.js": "6fca0322",
    "e4ea8fcc42d0f8dd381c.js": "bba68bf6",
    "f5a066701973d73408dd.js": "6936fa40",
    "ff01147a6b4f058ea8c7.js": "3abaccc1"
  }
}