{
  "publicPath": "https://file.calibur.tv/smile/",
  "all": [
    "../server/index.spa.html",
    "../server/index.ssr.html",
    "003aa3cff5df14f6c66b.js",
    "1bbfc452fd7a9cc2f008.js",
    "1c284fee128feff92820.js",
    "204bf672da15bbcff7b2.js",
    "2ddd829b826a90d4f8ac.js",
    "373aecca80cc58bd57ae.js",
    "3df1484a400e47c4e2e5.js",
    "43da8f4575283838e099.js",
    "4aff7632640fd483a0ed.js",
    "4b0e1ad5540eeae83a89.js",
    "553f1eb0fbe261768735.js",
    "5684ce016775a8c0f607.js",
    "6b2e2ffbbecfc4de066b.js",
    "6f77942632fa48e98a19.js",
    "7a08bf87f342f178f7cd.js",
    "978c2fa2923f686ae9ba.js",
    "9ab419781fc30f5775a2.js",
    "9bbecfe11864e54bad3d.js",
    "LICENSES",
    "a2811e5fbce2a6d4e597.js",
    "bc52d331e30b71a6309d.js",
    "ce345a1a38d5f5373b1c.js",
    "d005873d3754a8fe644b.js",
    "e94dc7763cb85cb9777e.js",
    "fb988114fb51ffbb003e.js"
  ],
  "initial": [
    "9ab419781fc30f5775a2.js",
    "1bbfc452fd7a9cc2f008.js",
    "bc52d331e30b71a6309d.js",
    "003aa3cff5df14f6c66b.js"
  ],
  "async": [
    "1c284fee128feff92820.js",
    "204bf672da15bbcff7b2.js",
    "2ddd829b826a90d4f8ac.js",
    "373aecca80cc58bd57ae.js",
    "3df1484a400e47c4e2e5.js",
    "43da8f4575283838e099.js",
    "4aff7632640fd483a0ed.js",
    "4b0e1ad5540eeae83a89.js",
    "553f1eb0fbe261768735.js",
    "5684ce016775a8c0f607.js",
    "6b2e2ffbbecfc4de066b.js",
    "6f77942632fa48e98a19.js",
    "7a08bf87f342f178f7cd.js",
    "978c2fa2923f686ae9ba.js",
    "9bbecfe11864e54bad3d.js",
    "a2811e5fbce2a6d4e597.js",
    "ce345a1a38d5f5373b1c.js",
    "d005873d3754a8fe644b.js",
    "e94dc7763cb85cb9777e.js",
    "fb988114fb51ffbb003e.js"
  ],
  "modules": {
    "12431467": [
      2
    ],
    "19127515": [
      9
    ],
    "29418593": [
      2
    ],
    "37431440": [
      3
    ],
    "49420837": [
      3
    ],
    "63245637": [
      3
    ],
    "74233369": [
      11
    ],
    "74871540": [
      3
    ],
    "81883058": [
      22
    ],
    "90955906": [
      3
    ],
    "3a010dac": [
      2
    ],
    "124e5295": [
      3
    ],
    "6f370d31": [
      3
    ],
    "54f0ac28": [
      3
    ],
    "6d2962e2": [
      3
    ],
    "1a8a7f94": [
      3
    ],
    "53d93926": [
      3
    ],
    "26e1e28a": [
      3
    ],
    "0361f436": [
      3
    ],
    "4ce68b47": [
      3
    ],
    "47f48e78": [
      3
    ],
    "c4144722": [
      3
    ],
    "2bba0d4a": [
      3
    ],
    "997000a8": [
      3
    ],
    "be8e635e": [
      3
    ],
    "9f3731e2": [
      3
    ],
    "08976508": [
      3
    ],
    "370f555c": [
      3
    ],
    "5fc3cd77": [
      3
    ],
    "44c9393a": [
      3
    ],
    "83b93d2e": [
      2
    ],
    "4086c90a": [
      2
    ],
    "09638930": [
      2
    ],
    "296d3250": [
      2
    ],
    "707f7e9f": [
      2
    ],
    "1d08d6da": [
      2
    ],
    "1dc862fa": [
      2
    ],
    "cda9a976": [
      2
    ],
    "20f637ba": [
      2
    ],
    "0420968e": [
      2
    ],
    "01e87044": [
      2
    ],
    "384bf3b8": [
      2
    ],
    "3f3fa777": [
      2
    ],
    "b8b0fa3a": [
      2
    ],
    "65660a26": [
      2
    ],
    "0d7e48f8": [
      2
    ],
    "b9dcdd5e": [
      2
    ],
    "b2929edc": [
      2
    ],
    "02e44889": [
      2
    ],
    "6a2ac987": [
      2
    ],
    "2f8f2786": [
      2
    ],
    "8bbc44f0": [
      2
    ],
    "e573ec18": [
      2
    ],
    "39711c24": [
      2
    ],
    "2870ec5a": [
      2
    ],
    "26445b32": [
      2
    ],
    "20b3df94": [
      2
    ],
    "cd1388b8": [
      2
    ],
    "cb76b8c2": [
      2
    ],
    "1e8f2b78": [
      2
    ],
    "41c016d1": [
      2
    ],
    "9f4c42ec": [
      2
    ],
    "4df5db58": [
      3
    ],
    "1d429c5f": [
      3
    ],
    "1b56b304": [
      3
    ],
    "aa328b9a": [
      3
    ],
    "3d799ad5": [
      3
    ],
    "39e3b82c": [
      3
    ],
    "6d8c28ae": [
      3
    ],
    "da8848cc": [
      3
    ],
    "dec9ed6a": [
      3
    ],
    "16876cac": [
      3
    ],
    "0c03a82c": [
      22
    ],
    "5709e04b": [
      22
    ],
    "3023fc8c": [
      22
    ],
    "9c3172ac": [
      3
    ],
    "5936ecf8": [
      3
    ],
    "212a25a0": [
      3
    ],
    "527f8644": [
      3
    ],
    "5407d911": [
      3
    ],
    "73fa3eb1": [
      3
    ],
    "e17f299a": [
      22
    ],
    "81a8320e": [
      3
    ],
    "b3b00f22": [
      3
    ],
    "5fc052e2": [
      3
    ],
    "20571c2c": [
      3
    ],
    "3cfda7be": [
      3
    ],
    "6cac6038": [
      3
    ],
    "1500d2ee": [
      22
    ],
    "c6a5f000": [
      3
    ],
    "3464832e": [
      3
    ],
    "9076cc1a": [
      3
    ],
    "0a9f248e": [
      3
    ],
    "4ba07f2b": [
      3
    ],
    "58dfee3f": [
      3
    ],
    "cd9b4ee2": [
      3
    ],
    "a2684fd6": [
      3
    ],
    "4cd96c01": [
      3
    ],
    "a422321c": [
      3
    ],
    "cbb40caa": [
      3
    ],
    "2180b99e": [
      3
    ],
    "f220fd9c": [
      3
    ],
    "2e0f8eb0": [
      3
    ],
    "2fd58a0e": [
      3
    ],
    "7b95e09c": [
      3
    ],
    "1f9f76a6": [
      3
    ],
    "e2051ba2": [
      3
    ],
    "84729f72": [
      3
    ],
    "f09a7938": [
      3
    ],
    "23f83252": [
      3
    ],
    "5cffe75c": [
      3
    ],
    "9aa35f58": [
      3
    ],
    "50e6ba1f": [
      3
    ],
    "1338daea": [
      3
    ],
    "d21ca04a": [
      2
    ],
    "60f4b76d": [
      2
    ],
    "78457b3a": [
      3
    ],
    "3aab9dfa": [
      3
    ],
    "1e777710": [
      3
    ],
    "425b7433": [
      3
    ],
    "5161995b": [
      3
    ],
    "74af09ee": [
      3
    ],
    "e8930af0": [
      3
    ],
    "437cb50c": [
      3
    ],
    "66f378f1": [
      3
    ],
    "10762a40": [
      3
    ],
    "96e2720e": [
      3
    ],
    "3c08a574": [
      3
    ],
    "defcb1a0": [
      3
    ],
    "a21bac8c": [
      3
    ],
    "00cafd6d": [
      3
    ],
    "8722180a": [
      3
    ],
    "636a4182": [
      3
    ],
    "b5892f56": [
      3
    ],
    "2179f1d1": [
      3
    ],
    "3998d7ca": [
      3
    ],
    "27ff73d2": [
      3
    ],
    "ec94d17c": [
      3
    ],
    "b86a6d86": [
      3
    ],
    "9cf82478": [
      3
    ],
    "5f40f880": [
      3
    ],
    "5f0e4f9a": [
      3
    ],
    "6de2d821": [
      2
    ],
    "1715f7c5": [
      22
    ],
    "e0f710b2": [
      3
    ],
    "15b6b9ac": [
      22
    ],
    "74ebb47b": [
      3
    ],
    "43cc0eb8": [
      3
    ],
    "453517ce": [
      3
    ],
    "0d849304": [
      3
    ],
    "2e9794fd": [
      3
    ],
    "740e29af": [
      3
    ],
    "1ab8eb8e": [
      3
    ],
    "4866aa68": [
      3
    ],
    "59104f6a": [
      3
    ],
    "3c1157ac": [
      3
    ],
    "6fc1c2c0": [
      3
    ],
    "70aee9f6": [
      3
    ],
    "40f8855a": [
      3
    ],
    "0eafc870": [
      3
    ],
    "88f435d4": [
      3
    ],
    "38e7e168": [
      3
    ],
    "1fa13b1c": [
      3
    ],
    "5ad0c49a": [
      3
    ],
    "480132c4": [
      3
    ],
    "be691254": [
      3
    ],
    "6e23840f": [
      3
    ],
    "19758ec0": [
      3
    ],
    "027533ee": [
      3
    ],
    "84b52944": [
      3
    ],
    "063bd2bc": [
      3
    ],
    "be42a8a4": [
      3
    ],
    "01a96b93": [
      3
    ],
    "3c2a35f5": [
      3
    ],
    "9b7d6cda": [
      3
    ],
    "5201c250": [
      3
    ],
    "c8a95d80": [
      3
    ],
    "41150bd4": [
      3
    ],
    "657deccf": [
      3
    ],
    "9a8358a4": [
      3
    ],
    "682719d0": [
      3
    ],
    "183399c3": [
      2
    ],
    "0a965e28": [
      3
    ],
    "5e0804f0": [
      3
    ],
    "f37f507c": [
      3
    ],
    "1581637e": [
      3
    ],
    "48d9c27c": [
      3
    ],
    "d01f8f52": [
      3
    ],
    "5074b669": [
      3
    ],
    "13a1e528": [
      3
    ],
    "609a0c0f": [
      22
    ],
    "3fceb88e": [
      3
    ],
    "59b79160": [
      22
    ],
    "242b964d": [
      22
    ],
    "774beee8": [
      22
    ],
    "81863e12": [
      22
    ],
    "01063421": [
      3
    ],
    "d07c648e": [
      3
    ],
    "4a95b443": [
      2
    ],
    "7605f570": [
      2
    ],
    "a1918aa8": [
      3
    ],
    "2df92de4": [
      3
    ],
    "2d60f209": [
      3
    ],
    "5060e930": [
      3
    ],
    "61a74a7d": [
      3
    ],
    "eedb2fa8": [
      3
    ],
    "e25a021a": [
      3
    ],
    "542c5260": [
      3
    ],
    "2543c6db": [
      3
    ],
    "5da0e2ba": [
      3
    ],
    "70ffb618": [
      3
    ],
    "02da218f": [
      3
    ],
    "33f761fc": [
      3
    ],
    "66d33e00": [
      3
    ],
    "56284d48": [
      3
    ],
    "5b388f66": [
      3
    ],
    "3080e4e0": [
      3
    ],
    "2bc7a946": [
      3
    ],
    "376cf570": [
      3
    ],
    "9cbce150": [
      3
    ],
    "01a3d328": [
      3
    ],
    "716d35b4": [
      3
    ],
    "483760fd": [
      3
    ],
    "4ba2b56a": [
      3
    ],
    "682ce779": [
      3
    ],
    "23a36203": [
      3
    ],
    "ec11f0a8": [
      3
    ],
    "c88e1d04": [
      3
    ],
    "2d750edc": [
      3
    ],
    "2cc5a251": [
      3
    ],
    "2d25c8db": [
      3
    ],
    "d85ea77e": [
      3
    ],
    "1c19066e": [
      3
    ],
    "76384d60": [
      3
    ],
    "0727feab": [
      2
    ],
    "1890545c": [
      2
    ],
    "4e20ef37": [
      2
    ],
    "5617989e": [
      2
    ],
    "a7a25434": [
      2
    ],
    "3d8c58d9": [
      2
    ],
    "3a292eb9": [
      2
    ],
    "3c348136": [
      3
    ],
    "d4f1f9a6": [
      3
    ],
    "6ab4a543": [
      3
    ],
    "139b1124": [
      3
    ],
    "eab7a366": [
      3
    ],
    "1b13dba0": [
      3
    ],
    "adba0600": [
      3
    ],
    "42fbc8f1": [
      3
    ],
    "30e8e021": [
      3
    ],
    "62bcd7c2": [
      3
    ],
    "fd8a53d4": [
      3
    ],
    "5a8593d4": [
      3
    ],
    "078f7efa": [
      3
    ],
    "b7850114": [
      3
    ],
    "3af8f9ae": [
      3
    ],
    "aedeb914": [
      3
    ],
    "260f971f": [
      22
    ],
    "1c4b1af0": [
      22
    ],
    "b86a823a": [
      22
    ],
    "e9f27986": [
      22
    ],
    "9a0a9e96": [
      2
    ],
    "5d5c4e34": [
      2
    ],
    "61d00072": [
      21
    ],
    "c9d509ce": [
      21
    ],
    "83f5345e": [
      10
    ],
    "60d3e5bb": [
      23
    ],
    "682784b0": [
      17
    ],
    "a7f10dd6": [
      24
    ],
    "4e42741a": [
      8
    ],
    "52b4dd13": [
      15
    ],
    "55a30d9c": [
      16
    ],
    "1d2e8465": [
      7
    ],
    "3b98767b": [
      26
    ],
    "44dd83c7": [
      19
    ],
    "744e60df": [
      4
    ],
    "591d3900": [
      11
    ],
    "8b214be6": [
      5
    ],
    "667261c1": [
      9
    ],
    "14800da1": [
      9
    ],
    "6ac47411": [
      10
    ],
    "58cfcdbe": [
      10
    ],
    "2d9adbdb": [
      21
    ],
    "9cfe410a": [
      23
    ],
    "0469cf24": [
      23
    ],
    "7e379be8": [
      17
    ],
    "42323fd5": [
      17
    ],
    "58c68755": [
      24
    ],
    "46d1e102": [
      24
    ],
    "77fd009a": [
      8
    ],
    "d13d48b4": [
      8
    ],
    "3dd796d3": [
      15
    ],
    "113772c6": [
      15
    ],
    "5987311c": [
      16
    ],
    "990dbac2": [
      16
    ],
    "3e4343b6": [
      7
    ],
    "08390898": [
      7
    ],
    "26bb303b": [
      26
    ],
    "0bc9e7a4": [
      26
    ],
    "d4eb04f2": [
      19
    ],
    "3c56930c": [
      19
    ],
    "24fa41c2": [
      4
    ],
    "f3c2fce8": [
      4
    ],
    "351f01c0": [
      11
    ],
    "78c23aa6": [
      11
    ],
    "50cd5e66": [
      12
    ],
    "634c50c4": [
      12
    ],
    "4d5361da": [
      12
    ],
    "1c1cf84d": [
      5
    ],
    "aac64d8c": [
      5
    ],
    "1fba3933": [
      9
    ],
    "a9258dac": [
      9
    ],
    "a8dc6d98": [
      9
    ],
    "40b23ffe": [
      9
    ],
    "7842826e": [
      9
    ],
    "762dabe1": [
      9
    ],
    "04ad8cce": [
      9
    ],
    "00721472": [
      19
    ],
    "326bb13e": [
      19
    ],
    "5f878dfc": [
      19
    ],
    "2260cab1": [
      19
    ],
    "20a55c16": [
      19
    ],
    "509e4df8": [
      19
    ],
    "dc150730": [
      19
    ],
    "770d32fc": [
      19
    ],
    "64b863b8": [
      19
    ],
    "49d689af": [
      19
    ],
    "41992ca4": [
      9
    ],
    "95bef1b2": [
      9
    ],
    "355e8bf0": [
      9
    ],
    "f5b5dc52": [
      9
    ],
    "e4cad596": [
      9
    ],
    "c54f2264": [
      9
    ],
    "8b0e5002": [
      9
    ],
    "a6980f30": [
      9
    ],
    "ea4eeaa2": [
      9
    ],
    "448b325e": [
      10
    ],
    "66764ac6": [
      10
    ],
    "5934a1d0": [
      10
    ],
    "a45d0d66": [
      10
    ],
    "deb519f6": [
      10
    ],
    "2d752628": [
      23
    ],
    "e646b8ee": [
      23
    ],
    "53270e88": [
      23
    ],
    "5f9f8ad9": [
      23
    ],
    "25f0653b": [
      23
    ],
    "bdb4c516": [
      17
    ],
    "ead63796": [
      17
    ],
    "632e4321": [
      17
    ],
    "2d088236": [
      17
    ],
    "4d74a14e": [
      17
    ],
    "440356a2": [
      24
    ],
    "d64552ee": [
      24
    ],
    "8f4fc158": [
      24
    ],
    "75e9f539": [
      24
    ],
    "7597e341": [
      24
    ],
    "0b35ed24": [
      8
    ],
    "25ed3d60": [
      8
    ],
    "f8e44760": [
      8
    ],
    "2d9098a0": [
      8
    ],
    "6e469603": [
      8
    ],
    "582bcc44": [
      15
    ],
    "1357d5e4": [
      15
    ],
    "62697da0": [
      15
    ],
    "53df0d34": [
      15
    ],
    "8cf80a3a": [
      15
    ],
    "449fd6ff": [
      16
    ],
    "5c7f280a": [
      16
    ],
    "6e4b3117": [
      16
    ],
    "08fe32ab": [
      16
    ],
    "3cfd3684": [
      16
    ],
    "0d42c1d4": [
      7
    ],
    "79962a52": [
      7
    ],
    "676321c4": [
      7
    ],
    "73affa27": [
      7
    ],
    "5845d15e": [
      7
    ],
    "675e3fac": [
      26
    ],
    "79924d86": [
      26
    ],
    "3c79f2c8": [
      26
    ],
    "8bccf654": [
      26
    ],
    "2732ac7b": [
      26
    ],
    "c690d528": [
      4
    ],
    "4f623fc9": [
      4
    ],
    "66a640ec": [
      4
    ],
    "1fc1f279": [
      4
    ],
    "390b5c37": [
      4
    ],
    "6424e74d": [
      11
    ],
    "65107d49": [
      11
    ],
    "4427be19": [
      11
    ],
    "0d5a5876": [
      11
    ],
    "5c4460f6": [
      6
    ],
    "634b231b": [
      6
    ],
    "16695bd1": [
      6
    ],
    "4457c1cb": [
      6
    ],
    "58adc084": [
      6
    ],
    "e4058744": [
      13
    ],
    "13e224b9": [
      13
    ],
    "2b72e518": [
      13
    ],
    "1622792e": [
      13
    ],
    "2e9aadf6": [
      13
    ],
    "a788c1a4": [
      14
    ],
    "97b2c3dc": [
      14
    ],
    "bd4b6770": [
      14
    ],
    "d599867c": [
      14
    ],
    "5e9a1035": [
      14
    ],
    "2308ddcc": [
      5
    ],
    "e9688da4": [
      5
    ],
    "0b3cf7c8": [
      5
    ],
    "5b5043de": [
      5
    ],
    "baa9416e": [
      5
    ],
    "216fcfc4": [
      25
    ],
    "529006cd": [
      25
    ],
    "65262a18": [
      25
    ],
    "b3352d06": [
      25
    ],
    "6ecea3c5": [
      25
    ]
  },
  "assetsMapping": {
    "003aa3cff5df14f6c66b.js": "1a3ae26b",
    "1bbfc452fd7a9cc2f008.js": "0859c165",
    "1c284fee128feff92820.js": "1d2d125f",
    "204bf672da15bbcff7b2.js": "6bdc928d",
    "2ddd829b826a90d4f8ac.js": "9e3fb090",
    "373aecca80cc58bd57ae.js": "748573da",
    "3df1484a400e47c4e2e5.js": "3ab85da1",
    "43da8f4575283838e099.js": "6bdfd521",
    "4aff7632640fd483a0ed.js": "ce4a41de",
    "4b0e1ad5540eeae83a89.js": "6936fa40",
    "553f1eb0fbe261768735.js": "3990566c",
    "5684ce016775a8c0f607.js": "9e3c2dde",
    "6b2e2ffbbecfc4de066b.js": "9e3b983e",
    "6f77942632fa48e98a19.js": "3abaccc1",
    "7a08bf87f342f178f7cd.js": "9a20429c",
    "978c2fa2923f686ae9ba.js": "4236c968",
    "9ab419781fc30f5775a2.js": "6fca0322",
    "9bbecfe11864e54bad3d.js": "ef652aa2",
    "a2811e5fbce2a6d4e597.js": "28662034",
    "bc52d331e30b71a6309d.js": "7ea1d828",
    "ce345a1a38d5f5373b1c.js": "23c1c72e",
    "d005873d3754a8fe644b.js": "cd107556",
    "e94dc7763cb85cb9777e.js": "2a130dde",
    "fb988114fb51ffbb003e.js": "3abf3429"
  }
}